odoo/addons/product_supplierinfo_for_customer_elaboration/README.rst
odoo/addons/product_supplierinfo_for_customer_elaboration/__init__.py
odoo/addons/product_supplierinfo_for_customer_elaboration/__manifest__.py
odoo/addons/product_supplierinfo_for_customer_elaboration/i18n/es.po
odoo/addons/product_supplierinfo_for_customer_elaboration/i18n/product_supplierinfo_for_customer_elaboration.pot
odoo/addons/product_supplierinfo_for_customer_elaboration/migrations/15.0.2.0.0/post-migration.py
odoo/addons/product_supplierinfo_for_customer_elaboration/migrations/15.0.2.0.0/pre-migration.py
odoo/addons/product_supplierinfo_for_customer_elaboration/models/__init__.py
odoo/addons/product_supplierinfo_for_customer_elaboration/models/product_customerinfo.py
odoo/addons/product_supplierinfo_for_customer_elaboration/models/sale_order_line.py
odoo/addons/product_supplierinfo_for_customer_elaboration/readme/CONFIGURE.rst
odoo/addons/product_supplierinfo_for_customer_elaboration/readme/CONTRIBUTORS.rst
odoo/addons/product_supplierinfo_for_customer_elaboration/readme/DESCRIPTION.rst
odoo/addons/product_supplierinfo_for_customer_elaboration/readme/USAGE.rst
odoo/addons/product_supplierinfo_for_customer_elaboration/security/ir.model.access.csv
odoo/addons/product_supplierinfo_for_customer_elaboration/static/description/icon.png
odoo/addons/product_supplierinfo_for_customer_elaboration/static/description/index.html
odoo/addons/product_supplierinfo_for_customer_elaboration/tests/__init__.py
odoo/addons/product_supplierinfo_for_customer_elaboration/tests/test_customerinfo_elaboration.py
odoo/addons/product_supplierinfo_for_customer_elaboration/views/product_views.xml
odoo_addon_product_supplierinfo_for_customer_elaboration-15.0.2.1.0.dist-info/METADATA
odoo_addon_product_supplierinfo_for_customer_elaboration-15.0.2.1.0.dist-info/WHEEL
odoo_addon_product_supplierinfo_for_customer_elaboration-15.0.2.1.0.dist-info/top_level.txt
odoo_addon_product_supplierinfo_for_customer_elaboration-15.0.2.1.0.dist-info/RECORD
