Metadata-Version: 2.1
Name: odoo-addon-product_supplierinfo_for_customer_elaboration
Version: 15.0.2.1.0
Summary: Allows to define default elaborations and elaboration notes on product customerinfos
Home-page: https://github.com/OCA/sale-workflow
Author: Tecnativa, Odoo Community Association (OCA)
Author-email: support@odoo-community.org
License: AGPL-3
Classifier: Programming Language :: Python
Classifier: Framework :: Odoo
Classifier: Framework :: Odoo :: 15.0
Classifier: License :: OSI Approved :: GNU Affero General Public License v3
Classifier: Development Status :: 4 - Beta
Requires-Python: >=3.8
Requires-Dist: odoo-addon-product-supplierinfo-for-customer-sale <15.1dev,>=15.0dev
Requires-Dist: odoo-addon-sale-elaboration <15.1dev,>=15.0dev
Requires-Dist: odoo <15.1dev,>=15.0a
